vhm_agent-0.1.1.data/scripts/core.py
vhm_agent-0.1.1.data/scripts/main.py
vhm_agent-0.1.1.data/scripts/vhm-agent
vhmlib/__init__.py
vhmlib/core.py
vhmlib/main.py
vhm_agent-0.1.1.dist-info/METADATA
vhm_agent-0.1.1.dist-info/WHEEL
vhm_agent-0.1.1.dist-info/top_level.txt
vhm_agent-0.1.1.dist-info/RECORD
