Metadata-Version: 2.1
Name: vhm-agent
Version: 0.1.1
Summary: Agent for manage system and project VHM.
Home-page: https://github.com/Pajinek/vhm
Author: Pavel Studenik
Author-email: studenik@varhoo.cz
License: GPL
Keywords: Client for Varhoo manage system
Platform: UNKNOWN
Classifier: Development Status :: 3 - Alpha
Classifier: Topic :: Utilities
Classifier: License :: OSI Approved :: GNU General Public License (GPL)
Classifier: Programming Language :: Python :: 2.7
Requires-Dist: psutil
Provides-Extra: psutil
Requires-Dist: python-psutil ; extra == 'psutil'
